LICENSE.txt
README.md
setup.cfg
setup.py
traktor_nml_utils/__init__.py
traktor_nml_utils/cli.py
traktor_nml_utils/utils.py
traktor_nml_utils.egg-info/PKG-INFO
traktor_nml_utils.egg-info/SOURCES.txt
traktor_nml_utils.egg-info/dependency_links.txt
traktor_nml_utils.egg-info/entry_points.txt
traktor_nml_utils.egg-info/requires.txt
traktor_nml_utils.egg-info/top_level.txt
traktor_nml_utils.egg-info/zip-safe
traktor_nml_utils/models/__init__.py
traktor_nml_utils/models/collection.py
traktor_nml_utils/models/history.py