Metadata-Version: 2.1
Name: traktor-nml-utils
Version: 3.1.0
Summary: Utilities to read and write Traktor NML files
Home-page: http://github.com/wolkenarchitekt/traktor-nml-utils
Author: Ingo Fischer
Author-email: mail@ingofischer.de
License: GPL
Platform: UNKNOWN
Requires-Python: >=3.7.0
